krutrim_cloud/__init__.py
krutrim_cloud/_base_client.py
krutrim_cloud/_client.py
krutrim_cloud/_compat.py
krutrim_cloud/_constants.py
krutrim_cloud/_exceptions.py
krutrim_cloud/_files.py
krutrim_cloud/_models.py
krutrim_cloud/_qs.py
krutrim_cloud/_resource.py
krutrim_cloud/_response.py
krutrim_cloud/_streaming.py
krutrim_cloud/_types.py
krutrim_cloud/_version.py
krutrim_cloud/py.typed
krutrim_cloud/_utils/__init__.py
krutrim_cloud/_utils/_logs.py
krutrim_cloud/_utils/_proxy.py
krutrim_cloud/_utils/_reflection.py
krutrim_cloud/_utils/_streams.py
krutrim_cloud/_utils/_sync.py
krutrim_cloud/_utils/_transform.py
krutrim_cloud/_utils/_typing.py
krutrim_cloud/_utils/_utils.py
krutrim_cloud/lib/prompt_registry.py
krutrim_cloud/lib/prompts.py
krutrim_cloud/lib/utils.py
krutrim_cloud/resources/__init__.py
krutrim_cloud/resources/audio/__init__.py
krutrim_cloud/resources/audio/audio.py
krutrim_cloud/resources/audio/transcriptions.py
krutrim_cloud/resources/audio/translations.py
krutrim_cloud/resources/chat/__init__.py
krutrim_cloud/resources/chat/chat.py
krutrim_cloud/resources/chat/completions.py
krutrim_cloud/resources/deploy/__init__.py
krutrim_cloud/resources/deploy/deploy.py
krutrim_cloud/resources/deploy/tasks.py
krutrim_cloud/resources/fine_tuning/__init__.py
krutrim_cloud/resources/fine_tuning/datasets.py
krutrim_cloud/resources/fine_tuning/fine_tuning.py
krutrim_cloud/resources/fine_tuning/tasks.py
krutrim_cloud/resources/fine_tuning/engines/__init__.py
krutrim_cloud/resources/fine_tuning/engines/engines.py
krutrim_cloud/resources/fine_tuning/engines/model/__init__.py
krutrim_cloud/resources/fine_tuning/engines/model/mode.py
krutrim_cloud/resources/fine_tuning/engines/model/model.py
krutrim_cloud/resources/fine_tuning/models/__init__.py
krutrim_cloud/resources/fine_tuning/models/mode.py
krutrim_cloud/resources/fine_tuning/models/models.py
krutrim_cloud/resources/fine_tuning/modes/__init__.py
krutrim_cloud/resources/fine_tuning/modes/model.py
krutrim_cloud-0.7.1.dist-info/METADATA
krutrim_cloud-0.7.1.dist-info/WHEEL
krutrim_cloud-0.7.1.dist-info/licenses/LICENSE
krutrim_cloud-0.7.1.dist-info/RECORD
