Metadata-Version: 2.4
Name: krutrim_cloud
Version: 0.7.1
Summary: The official Python library for the Krutrim Cloud API
Project-URL: Homepage, https://github.com/ola-krutrim/krutrim-cloud-python
Project-URL: Repository, https://github.com/ola-krutrim/krutrim-cloud-python
Author-email: Krutrim Cloud <cloudsupport@olakrutrim.com>
License:                                  Apache License
License-File: LICENSE
Classifier: Intended Audience :: Developers
Classifier: License :: OSI Approved :: Apache Software License
Classifier: Operating System :: MacOS
Classifier: Operating System :: Microsoft :: Windows
Classifier: Operating System :: OS Independent
Classifier: Operating System :: POSIX
Classifier: Operating System :: POSIX :: Linux
Classifier: Programming Language :: Python :: 3.10
Classifier: Programming Language :: Python :: 3.11
Classifier: Programming Language :: Python :: 3.12
Classifier: Topic :: Software Development :: Libraries :: Python Modules
Classifier: Typing :: Typed
Requires-Python: <3.13,>=3.10
Requires-Dist: anyio<5,>=3.5.0
Requires-Dist: boto3>=1.35.8
Requires-Dist: cached-property; python_version < '3.8'
Requires-Dist: distro<2,>=1.7.0
Requires-Dist: httpx<1,>=0.23.0
Requires-Dist: jupyter>=1.1.1
Requires-Dist: moviepy<2,>=1.0.3
Requires-Dist: notebook>=7.2.2
Requires-Dist: numpy>=2.1.0
Requires-Dist: opencv-python>=4.10.0
Requires-Dist: pillow>=9.3.0
Requires-Dist: pydantic<3,>=1.9.0
Requires-Dist: pydub>=0.25.1
Requires-Dist: python-dotenv>=0.10
Requires-Dist: sniffio
Requires-Dist: typing-extensions<5,>=4.7
